check_dep_updates/__init__.py
check_dep_updates/py.typed
check_dep_updates-0.2.0.dist-info/METADATA
check_dep_updates-0.2.0.dist-info/WHEEL
check_dep_updates-0.2.0.dist-info/entry_points.txt
check_dep_updates-0.2.0.dist-info/top_level.txt
check_dep_updates-0.2.0.dist-info/RECORD
