Metadata-Version: 2.1
Name: check-dep-updates
Version: 0.2.0
Summary: Dependency Update Checker for Pip
Home-page: https://github.com/cheeseandcereal/check-dep-updates
Author: Adam Crowder
License: Unlicense
Project-URL: Source, https://github.com/cheeseandcereal/check-dep-updates
Project-URL: Bug Tracker, https://github.com/cheeseandcereal/check-dep-updates/issues
Platform: UNKNOWN
Classifier: Development Status :: 3 - Alpha
Classifier: Intended Audience :: Developers
Classifier: License :: Public Domain
Classifier: Operating System :: POSIX
Classifier: Operating System :: MacOS :: MacOS X
Classifier: Operating System :: Microsoft :: Windows
Classifier: Natural Language :: English
Classifier: Programming Language :: Python
Classifier: Programming Language :: Python :: 3
Classifier: Programming Language :: Python :: 3.6
Classifier: Programming Language :: Python :: 3.7
Classifier: Programming Language :: Python :: 3.8
Classifier: Typing :: Typed
Requires-Python: >=3.6
Requires-Dist: pip
